gzdice/__init__.py
gzdice/__main__.py
gzdice/RPG_systems/__init.py__
gzdice/RPG_systems/existing_system.py
gzdice/RPG_systems/new_system.py
gzdice/data/RPGDictionary.py
gzdice/menus/__init.py__
gzdice/menus/base_menus.py
gzdice/rollers/BucketOfDice.py
gzdice/rollers/ExplodingDice.py
gzdice/rollers/FateRoller.py
gzdice/rollers/PolyhedralRoller.py
gzdice/rollers/StarWarsDice.py
gzdice/rollers/__init.py__
gzdice-0.1.2.dist-info/entry_points.txt
gzdice-0.1.2.dist-info/LICENSE
gzdice-0.1.2.dist-info/WHEEL
gzdice-0.1.2.dist-info/METADATA
gzdice-0.1.2.dist-info/RECORD
